molr/__init__.py
molr/config.py
molr/bond_detection/__init__.py
molr/bond_detection/default_detector.py
molr/ccd/__init__.py
molr/ccd/ccd_analyzer.py
molr/ccd/constants_generator.py
molr/ccd/generate_ccd_constants.py
molr/constants/__init__.py
molr/constants/atomic_data.py
molr/constants/bond_parameters.py
molr/constants/pdb_constants.py
molr/constants/residue_bonds.py
molr/core/__init__.py
molr/core/bond_list.py
molr/core/connectivity.py
molr/core/realm.py
molr/core/structure.py
molr/core/structure_ensemble.py
molr/io/__init__.py
molr/io/mmcif.py
molr/io/pdb.py
molr/selection/__init__.py
molr/selection/engine.py
molr/selection/expressions.py
molr/selection/parser.py
molr/topology/__init__.py
molr/utilities/__init__.py
molr/utilities/atom_utils.py
molr/utils/__init__.py
molr-0.1.0.dist-info/licenses/LICENSE
molr-0.1.0.dist-info/METADATA
molr-0.1.0.dist-info/WHEEL
molr-0.1.0.dist-info/top_level.txt
molr-0.1.0.dist-info/RECORD
