Metadata-Version: 2.4
Name: molr
Version: 0.1.0
Summary: Molecular Realm for Spatial Indexed Structures - Fast spatial operations for molecular data
Home-page: https://github.com/abhishektiwari/molr
Author: Abhishek Tiwari
Author-email: 
License: MIT
Project-URL: Homepage, https://github.com/abhishektiwari/molr
Project-URL: Documentation, https://molr.abhishek-tiwari.com/
Project-URL: Repository, https://github.com/abhishektiwari/molr.git
Project-URL: Issues, https://github.com/abhishektiwari/molr/issues
Keywords: molecular,structure,chemistry,bioinformatics,pdb,spatial-indexing
Classifier: Development Status :: 3 - Alpha
Classifier: Intended Audience :: Science/Research
Classifier: Topic :: Scientific/Engineering :: Bio-Informatics
Classifier: Topic :: Scientific/Engineering :: Chemistry
Classifier: License :: OSI Approved :: MIT License
Classifier: Programming Language :: Python :: 3
Classifier: Programming Language :: Python :: 3.8
Classifier: Programming Language :: Python :: 3.9
Classifier: Programming Language :: Python :: 3.10
Classifier: Programming Language :: Python :: 3.11
Classifier: Programming Language :: Python :: 3.12
Requires-Python: >=3.8
License-File: LICENSE
Requires-Dist: numpy>=1.20.0
Requires-Dist: scipy>=1.7.0
Requires-Dist: pyparsing>=3.0.0
Requires-Dist: pdbreader>=0.1.0
Requires-Dist: mmcif>=0.1.0
Provides-Extra: dev
Requires-Dist: pytest>=7.0.0; extra == "dev"
Requires-Dist: pytest-cov>=4.0.0; extra == "dev"
Requires-Dist: black>=22.0.0; extra == "dev"
Requires-Dist: mypy>=1.0.0; extra == "dev"
Requires-Dist: flake8>=6.0.0; extra == "dev"
Requires-Dist: isort>=5.0.0; extra == "dev"
Provides-Extra: docs
Requires-Dist: sphinx>=5.0.0; extra == "docs"
Requires-Dist: sphinx-rtd-theme>=1.0.0; extra == "docs"
Requires-Dist: sphinx-autodoc-typehints>=1.0.0; extra == "docs"
Dynamic: home-page
Dynamic: license-file
Dynamic: requires-python
